boom/notebooks/dataset_utils.py
boom/notebooks/vis_forecast.py
boom/utils/breakdown.py
boom/utils/leaderboard.py
toto/__init__.py
toto/data/__init__.py
toto/data/util/__init__.py
toto/data/util/dataset.py
toto/evaluation/run_lsf_eval.py
toto/evaluation/lsf/lsf_datasets.py
toto/evaluation/lsf/lsf_evaluator.py
toto/inference/__init__.py
toto/inference/forecaster.py
toto/inference/gluonts_predictor.py
toto/model/__init__.py
toto/model/attention.py
toto/model/backbone.py
toto/model/distribution.py
toto/model/embedding.py
toto/model/feed_forward.py
toto/model/rope.py
toto/model/scaler.py
toto/model/toto.py
toto/model/transformer.py
toto/model/util.py
toto/test/__init__.py
toto/test/helper_functions.py
toto/test/inference/__init__.py
toto/test/inference/forecaster_test.py
toto/test/inference/gluonts_predictor_test.py
toto/test/model/__init__.py
toto/test/model/attention_test.py
toto/test/model/scaler_test.py
toto_ts-0.1.3.dist-info/licenses/LICENSE
toto_ts-0.1.3.dist-info/licenses/LICENSE-3rdparty.csv
toto_ts-0.1.3.dist-info/licenses/NOTICE
toto_ts-0.1.3.dist-info/METADATA
toto_ts-0.1.3.dist-info/WHEEL
toto_ts-0.1.3.dist-info/top_level.txt
toto_ts-0.1.3.dist-info/RECORD
