Metadata-Version: 2.4
Name: toto-ts
Version: 0.1.3
Summary: Time-Series-Optimized Transformer for Observability
Author: DataDog, Inc.
License: Apache-2.0
Requires-Python: >=3.10
License-File: LICENSE
License-File: LICENSE-3rdparty.csv
License-File: NOTICE
Requires-Dist: torch==2.7.0
Requires-Dist: aioboto3==12.4.0
Requires-Dist: beartype==0.18.5
Requires-Dist: boto3==1.34.69
Requires-Dist: datasets==2.17.1
Requires-Dist: dill==0.3.8
Requires-Dist: einops==0.7.0
Requires-Dist: gluonts[torch]==0.15.1
Requires-Dist: jaxtyping==0.2.29
Requires-Dist: mypy==1.11.1
Requires-Dist: pandas==2.2.3
Requires-Dist: pytest==8.3.5
Requires-Dist: pytest-env==1.1.5
Requires-Dist: rotary-embedding-torch==0.8.6
Requires-Dist: scikit-learn==1.5.0
Requires-Dist: types-tabulate==0.9.0.20241207
Requires-Dist: transformers==4.52.1
Requires-Dist: tqdm==4.66.3
Requires-Dist: beartype==0.18.5
Requires-Dist: mypy==1.11.1
Requires-Dist: pyyaml==6.0.2
Requires-Dist: types-PyYAML==6.0.12.20240917
Requires-Dist: black==24.10.0
Requires-Dist: isort==5.13.2
Requires-Dist: PyYAML==6.0.2
Requires-Dist: jupyter==1.1.1
Requires-Dist: matplotlib==3.9.2
Requires-Dist: tabulate==0.9.0
Dynamic: license-file
